AnsiCMianxiangduixiangbiancheng/README.md
AnsiCMianxiangduixiangbiancheng/__init__.py
AnsiCMianxiangduixiangbiancheng/__main__.py
AnsiCMianxiangduixiangbiancheng/file.epub
AnsiCMianxiangduixiangbiancheng/index.html
AnsiCMianxiangduixiangbiancheng/css/__init__.py
AnsiCMianxiangduixiangbiancheng/css/annotations.css
AnsiCMianxiangduixiangbiancheng/css/main.css
AnsiCMianxiangduixiangbiancheng/css/normalize.css
AnsiCMianxiangduixiangbiancheng/css/popup.css
AnsiCMianxiangduixiangbiancheng/font/__init__.py
AnsiCMianxiangduixiangbiancheng/font/fontello.eot
AnsiCMianxiangduixiangbiancheng/font/fontello.svg
AnsiCMianxiangduixiangbiancheng/font/fontello.ttf
AnsiCMianxiangduixiangbiancheng/font/fontello.woff
AnsiCMianxiangduixiangbiancheng/img/__init__.py
AnsiCMianxiangduixiangbiancheng/img/annotator-glyph-sprite.png
AnsiCMianxiangduixiangbiancheng/img/annotator-icon-sprite.png
AnsiCMianxiangduixiangbiancheng/img/apple-touch-icon.png
AnsiCMianxiangduixiangbiancheng/img/cancelfullscreen.png
AnsiCMianxiangduixiangbiancheng/img/close.png
AnsiCMianxiangduixiangbiancheng/img/fullscreen.png
AnsiCMianxiangduixiangbiancheng/img/loader.gif
AnsiCMianxiangduixiangbiancheng/img/menu-icon.png
AnsiCMianxiangduixiangbiancheng/img/save.png
AnsiCMianxiangduixiangbiancheng/img/saved.png
AnsiCMianxiangduixiangbiancheng/img/settings-s.png
AnsiCMianxiangduixiangbiancheng/img/settings.png
AnsiCMianxiangduixiangbiancheng/img/star.png
AnsiCMianxiangduixiangbiancheng/js/__init__.py
AnsiCMianxiangduixiangbiancheng/js/epub.js
AnsiCMianxiangduixiangbiancheng/js/epub.min.js
AnsiCMianxiangduixiangbiancheng/js/epub.min.map
AnsiCMianxiangduixiangbiancheng/js/hooks.min.js
AnsiCMianxiangduixiangbiancheng/js/hooks.min.map
AnsiCMianxiangduixiangbiancheng/js/reader.js
AnsiCMianxiangduixiangbiancheng/js/reader.js.map
AnsiCMianxiangduixiangbiancheng/js/reader.min.js
AnsiCMianxiangduixiangbiancheng/js/reader.min.map
AnsiCMianxiangduixiangbiancheng/js/hooks/__init__.py
ansi_c_mianxiangduixiangbiancheng-2024.2.29.0.dist-info/METADATA
ansi_c_mianxiangduixiangbiancheng-2024.2.29.0.dist-info/WHEEL
ansi_c_mianxiangduixiangbiancheng-2024.2.29.0.dist-info/entry_points.txt
ansi_c_mianxiangduixiangbiancheng-2024.2.29.0.dist-info/top_level.txt
ansi_c_mianxiangduixiangbiancheng-2024.2.29.0.dist-info/RECORD
